microlog/__init__.py
microlog/microlog.py
microlog-0.1.0.dist-info/LICENSE
microlog-0.1.0.dist-info/METADATA
microlog-0.1.0.dist-info/WHEEL
microlog-0.1.0.dist-info/top_level.txt
microlog-0.1.0.dist-info/RECORD
