Metadata-Version: 2.1
Name: microlog
Version: 0.1.0
Summary: A simple and lightweight logging library
Home-page: https://github.com/bsacash/microlog
Author: Brian Sacash
License: UNKNOWN
Platform: UNKNOWN
Classifier: Programming Language :: Python :: 3
Classifier: License :: OSI Approved :: MIT License
Classifier: Operating System :: OS Independent
